mtehis/__init__.py
mtehis/version.py
mtehis/base/__init__.py
mtehis/base/detector.py
mtehis/data/__init__.py
mtehis/data/detector.py
mtehis/model/__init__.py
mtehis/model/classifier.py
mtehis/model/detector.py
mtehis/util/__init__.py
mtehis/util/evaluate.py
mtehis-0.1.3.dist-info/LICENSE
mtehis-0.1.3.dist-info/METADATA
mtehis-0.1.3.dist-info/WHEEL
mtehis-0.1.3.dist-info/top_level.txt
mtehis-0.1.3.dist-info/RECORD
