Metadata-Version: 2.1
Name: mtehis
Version: 0.1.3
Summary: Maintenance Tool for Evolving Hybrid Intelligent Systems: Core Package.
Home-page: https://github.com/MT-EHIS/core
Author: Oleksandr Pokhylenko
Author-email: pokhilenko.alex@gmail.com
License: UNKNOWN
Platform: all
Classifier: Intended Audience :: Developers
Classifier: Intended Audience :: Education
Classifier: Intended Audience :: Science/Research
Classifier: Intended Audience :: Information Technology
Classifier: Programming Language :: Python :: 3.9
Classifier: License :: OSI Approved :: Apache Software License
Classifier: Operating System :: OS Independent
License-File: LICENSE
Requires-Dist: streamad (==0.3.0)
